weighting/__init__.py
weighting-1.2.0.dist-info/LICENSE
weighting-1.2.0.dist-info/METADATA
weighting-1.2.0.dist-info/WHEEL
weighting-1.2.0.dist-info/top_level.txt
weighting-1.2.0.dist-info/RECORD
