Metadata-Version: 2.1
Name: weighting
Version: 1.2.0
Summary: functions to calculate weights
Author: atzur
Project-URL: homepage, https://github.com/atzuur/weighting
Classifier: Programming Language :: Python :: 3
Classifier: License :: OSI Approved :: MIT License
Classifier: Operating System :: OS Independent
Requires-Python: >=3.10
License-File: LICENSE
